{"name":"Lunch-and-learn","tagline":"A collection of samples for learning purposes","body":"# Bit Space Development Lunch & Learn\r\nAt Bit Space Development Ltd we are always working to innovate and learn. This repository is a collection of projects that were created for learning purposes. This is a collection of code we have written for the sole purpose of learning within our organization.\r\n\r\n## Lunch & Learn\r\nA Lunch & Learn is not a complex thing. It is esentially a team having lunch together while a team member presents on a new topic that they are either interested in or think it will benefit the technical skills of the team.\r\n\r\n## Topics\r\nThis list will be updated each time there is a new topic added to the repository.\r\n1. [Angular JS](https://github.com/BitSpaceDevelopment/lunch-and-learn/tree/master/1-angularjs)\r\n\r\n## Upcoming Topics\r\n1. Laravel\r\n2. Ionic\r\n3. Lumen\r\n4. JSPM\r\n5. Google App Engine\r\n","google":"","note":"Don't delete this file! It's used internally to help with page regeneration."}